README.md
setup.py
aviatrix/__init__.py
aviatrix_sdk.egg-info/PKG-INFO
aviatrix_sdk.egg-info/SOURCES.txt
aviatrix_sdk.egg-info/dependency_links.txt
aviatrix_sdk.egg-info/top_level.txt