Metadata-Version: 1.0
Name: aviatrix-sdk
Version: 0.9.4
Summary: Aviatrix Python SDK
Home-page: https://aviatrix.com
Author: Aviatrix Solution Architects
Author-email: info@aviatrix.com
License: UNKNOWN
Platform: UNKNOWN
